ocrdataextractor/__init__.py
ocrdataextractor-0.1.dist-info/LICENCE.txt
ocrdataextractor-0.1.dist-info/METADATA
ocrdataextractor-0.1.dist-info/WHEEL
ocrdataextractor-0.1.dist-info/top_level.txt
ocrdataextractor-0.1.dist-info/RECORD
