Metadata-Version: 2.1
Name: ocrdataextractor
Version: 0.1
Summary: Proteus data extractor File
Home-page: UNKNOWN
Author: Proteus Technology PVT. LTD.
Author-email: <aniket.gadge@proteustech.in>
License: UNKNOWN
Keywords: python,first package
Platform: UNKNOWN
Classifier: Development Status :: 3 - Alpha
Classifier: Intended Audience :: Education
Classifier: Programming Language :: Python :: 2
Classifier: Programming Language :: Python :: 3
Classifier: Operating System :: MacOS :: MacOS X
Classifier: Operating System :: Microsoft :: Windows
License-File: LICENCE.txt
Requires-Dist: pdf2image
Requires-Dist: pytesseract
Requires-Dist: invoice2data
Requires-Dist: read-cheque
Requires-Dist: fitz
Requires-Dist: pathlib
Requires-Dist: pdfkit
Requires-Dist: flask
